approx/__init__.py
approx/core/__init__.py
approx/core/_vars.py
approx/core/api.py
approx/core/backend/__init__.py
approx/core/backend/_backend.py
approx/core/backend/common.py
approx/core/device/__init__.py
approx/core/device/_device.py
approx/core/device/common.py
approx/core/quant/__init__.py
approxlib-0.1.0.dist-info/LICENSE
approxlib-0.1.0.dist-info/WHEEL
approxlib-0.1.0.dist-info/METADATA
approxlib-0.1.0.dist-info/RECORD
